LICENSE
MANIFEST.in
README
setup.py
answrs/__init__.py
answrs/admin.py
answrs/aforms.py
answrs/models.py
answrs/urls.py
answrs/views.py
answrs/templates/answrs/add_cat.html
answrs/templates/answrs/answers.html
answrs/templates/answrs/ask.html
answrs/templates/answrs/base.html
answrs/templates/answrs/index.html
answrs/templates/answrs/profile.html
django_answrs.egg-info/PKG-INFO
django_answrs.egg-info/SOURCES.txt
django_answrs.egg-info/dependency_links.txt
django_answrs.egg-info/not-zip-safe
django_answrs.egg-info/top_level.txt